aiden/__init__.py
aiden/agents/__init__.py
aiden/agents/aiden.py
aiden/agents/data_engineer.py
aiden/agents/data_expert.py
aiden/agents/manager.py
aiden/callbacks.py
aiden/common/__init__.py
aiden/common/dataset.py
aiden/common/environment.py
aiden/common/provider.py
aiden/common/utils/__init__.py
aiden/common/utils/cot/__init__.py
aiden/common/utils/cot/adapters.py
aiden/common/utils/cot/callable.py
aiden/common/utils/cot/emitters.py
aiden/common/utils/cot/protocol.py
aiden/common/utils/prompt.py
aiden/common/utils/pydantic_utils.py
aiden/common/utils/response.py
aiden/common/utils/transformation_state.py
aiden/common/utils/transformation_utils.py
aiden/config.py
aiden/entities/__init__.py
aiden/entities/code.py
aiden/entities/description.py
aiden/entities/node.py
aiden/executors/__init__.py
aiden/executors/docker_executor.py
aiden/executors/executor.py
aiden/executors/local_executor.py
aiden/generators/__init__.py
aiden/generators/code_generator.py
aiden/prompts/code_generator/fix.jinja
aiden/prompts/code_generator/generate.jinja
aiden/prompts/code_generator/review.jinja
aiden/prompts/code_generator/system_prompt.jinja
aiden/prompts/data_engineer_prompt_templates.yaml
aiden/prompts/data_expert_prompt_templates.yaml
aiden/prompts/manager_prompt.jinja
aiden/prompts/manager_prompt_templates.yaml
aiden/prompts/utils/cot_summarize.jinja
aiden/prompts/utils/system_prompt.jinja
aiden/registries/__init__.py
aiden/registries/objects.py
aiden/tools/__init__.py
aiden/tools/code_generation.py
aiden/tools/execution.py
aiden/tools/response_formatting.py
aiden/transformations.py
aiden_ai-0.2.0.dist-info/LICENSE
aiden_ai-0.2.0.dist-info/METADATA
aiden_ai-0.2.0.dist-info/WHEEL
aiden_ai-0.2.0.dist-info/entry_points.txt
aiden_ai-0.2.0.dist-info/RECORD
