Metadata-Version: 2.3
Name: aiden-ai
Version: 0.2.0
Summary: An agentic framework for building Data transformations from natural language
License: Apache-2.0
Keywords: agent,custom ai,llm,data transformation,data engineering
Author: hamza sefiane
Author-email: h.sefiane7@gmail.com
Requires-Python: >=3.11,<3.13
Classifier: Development Status :: 3 - Alpha
Classifier: Intended Audience :: Developers
Classifier: Intended Audience :: Science/Research
Classifier: License :: OSI Approved :: Apache Software License
Classifier: Programming Language :: Python :: 3
Classifier: Programming Language :: Python :: 3.11
Classifier: Programming Language :: Python :: 3.12
Classifier: Topic :: Scientific/Engineering :: Artificial Intelligence
Classifier: Topic :: Software Development :: Libraries :: Python Modules
Provides-Extra: dagster
Requires-Dist: black (>=24.10.0,<25.0.0)
Requires-Dist: click (>=8.1.7,<9.0.0)
Requires-Dist: dagster (>=1.10.15,<2.0.0) ; extra == "dagster"
Requires-Dist: dagster-webserver (>=1.10.15,<2.0.0) ; extra == "dagster"
Requires-Dist: dataclasses-json (>=0.6.7,<0.7.0)
Requires-Dist: hypothesis (>=6.125.1,<7.0.0)
Requires-Dist: jinja2 (>=3.1.6,<4.0.0)
Requires-Dist: joblib (>=1.4.2,<2.0.0)
Requires-Dist: litellm (==1.65.8)
Requires-Dist: numpy (>=1.23.2,<2.0.0)
Requires-Dist: pandas (>=1.5.0,<=2.2.0)
Requires-Dist: platformdirs (>=4.3.7,<5.0.0)
Requires-Dist: pyarrow (>=19.0.0,<20.0.0)
Requires-Dist: pydantic (>=2.9.2,<3.0.0)
Requires-Dist: rich (>=13.7.1,<14.0.0)
Requires-Dist: smolagents (>=1.15.0,<2.0.0)
Requires-Dist: tenacity (>=9.0.0,<10.0.0)
Project-URL: Homepage, https://github.com/getaiden/aiden
Project-URL: Repository, https://github.com/getaiden/aiden
